pyqt_svg_label/__init__.py
pyqt_svg_label/svgLabel.py
pyqt_svg_label-0.0.13.dist-info/LICENSE
pyqt_svg_label-0.0.13.dist-info/METADATA
pyqt_svg_label-0.0.13.dist-info/WHEEL
pyqt_svg_label-0.0.13.dist-info/top_level.txt
pyqt_svg_label-0.0.13.dist-info/RECORD
