Metadata-Version: 2.1
Name: pyqt-svg-label
Version: 0.0.13
Summary: PyQt QLabel which supports SVG icon
Home-page: https://github.com/yjg30737/pyqt-svg-label.git
Author: Jung Gyu Yoon
Author-email: yjg30737@gmail.com
License: MIT
License-File: LICENSE
Requires-Dist: PyQt5 (>=5.8)
Requires-Dist: absresgetter (>=0.0.1)
